open_alchemy/__init__.py
open_alchemy/package_security/__init__.py
open_alchemy/package_security/config.py
open_alchemy/package_security/pytest_plugin.py
open_alchemy/package_security/types.py
open_alchemy.package_security-1.2.1.dist-info/entry_points.txt
open_alchemy.package_security-1.2.1.dist-info/WHEEL
open_alchemy.package_security-1.2.1.dist-info/METADATA
open_alchemy.package_security-1.2.1.dist-info/RECORD
