Metadata-Version: 2.1
Name: open-alchemy.package-security
Version: 1.2.1
Summary: Security helper for the OpenAlchemy package service
License: Apache-2.0
Author: David Andersson
Author-email: jdkandersson@users.noreply.github.com
Requires-Python: >=3.8,<4.0
Classifier: License :: OSI Approved :: Apache Software License
Classifier: Programming Language :: Python :: 3
Classifier: Programming Language :: Python :: 3.8
Classifier: Programming Language :: Python :: 3.9
Requires-Dist: boto3 (>=1.16.47,<2.0.0)
